bybit_mcp/__init__.py
bybit_mcp/main.py
bybit_mcp/market.py
bybit_mcp/position.py
bybit_mcp/trade.py
bybit_mcp/models/market_models.py
bybit_mcp/models/position_models.py
bybit_mcp/models/trade_models.py
bybit_mcp-0.1.10.dist-info/METADATA
bybit_mcp-0.1.10.dist-info/WHEEL
bybit_mcp-0.1.10.dist-info/entry_points.txt
bybit_mcp-0.1.10.dist-info/RECORD
