Metadata-Version: 2.4
Name: bybit-mcp
Version: 0.1.10
Summary: Bybit MCP Server - Model Context Protocol implementation for Bybit trading API
Project-URL: Homepage, https://github.com/BCusack/bybit-py-mcp
Project-URL: Issues, https://github.com/BCusack/bybit-py-mcp/issues
Author-email: Brian Cusack <briancusack78@gmail.com>
Requires-Python: >=3.13
Requires-Dist: mcp>=1.1.0
Requires-Dist: pybit>=5.11.0
Requires-Dist: pydantic>=2.11.5
Requires-Dist: python-dotenv>=1.1.0
